datagit/__init__.py
datagit/cli.py
datagit/datagit.py
datagit/dataset_helpers.py
datagit/drift_evaluators.py
datagit/drift_evaluators_dry_run.py
datagit/github_connector.py
datagit/query_builder.py
tests/__init__.py
tests/test_compare_dataframes.py
tests/test_git_helpers.py
tests/test_github_connector.py
tests/test_large_dataset_comparison.py
tests/test_parse_date.py
tests/test_query_builder.py
datagit-0.18.6.dist-info/METADATA
datagit-0.18.6.dist-info/WHEEL
datagit-0.18.6.dist-info/entry_points.txt
datagit-0.18.6.dist-info/top_level.txt
datagit-0.18.6.dist-info/RECORD
