Metadata-Version: 2.1
Name: datagit
Version: 0.18.6
Summary: Git based metric store
Home-page: https://github.com/data-drift/data-drift/tree/main/tools/datagit
Author: Sammy Teillet
Author-email: sammy.teillet@gmail.com
Classifier: Programming Language :: Python :: 3
Classifier: License :: OSI Approved :: MIT License
Classifier: Operating System :: OS Independent
Requires-Python: >=3.6
Requires-Dist: pandas
Requires-Dist: PyGithub
Requires-Dist: click
